bl_event_sourcing/__init__.py
bl_event_sourcing/core.py
bl_event_sourcing/ddd.py
bl_event_sourcing/py.typed
bl_event_sourcing/utils.py
bl_event_sourcing-0.3.0.dist-info/LICENSE.md
bl_event_sourcing-0.3.0.dist-info/METADATA
bl_event_sourcing-0.3.0.dist-info/WHEEL
bl_event_sourcing-0.3.0.dist-info/RECORD
